xpl/__init__.py
xpl/console/__init__.py
xpl/console/console.py
xpl/container/__init__.py
xpl/container/dictionary.py
xpl/core/__init__.py
xpl/core/anonymousclass.py
xpl/core/asynceventhandler.py
xpl/core/baseclass.py
xpl/core/baseconstant.py
xpl/core/basemetaclass.py
xpl/core/basenode.py
xpl/core/enumflag.py
xpl/core/eventhandler.py
xpl/core/interface.py
xpl/core/managedobject.py
xpl/core/reflection.py
xpl/core/weakedreference.py
xpl/dataformat/__init__.py
xpl/dataformat/ini/__init__.py
xpl/dataformat/json/__init__.py
xpl/dataformat/xml/__init__.py
xpl/dataformat/xml/document.py
xpl/dataformat/xml/element.py
xpl/dataformat/xml/path.py
xpl/decorator/__init__.py
xpl/decorator/decorator_classproperty.py
xpl/decorator/decorator_overridemethod.py
xpl/deprecated/__init__.py
xpl/deprecated/basenode.py
xpl/deprecated/decorator.py
xpl/deprecated/logger.py
xpl/deprecated/dom/__init__.py
xpl/deprecated/dom/lazyxmldocument.py
xpl/deprecated/dom/lazyxmlelement.py
xpl/ecs/__init__.py
xpl/ecs/component.py
xpl/ecs/entity.py
xpl/ecs/system.py
xpl/environment/__init__.py
xpl/environment/environment.py
xpl/environment/exitcodetype.py
xpl/environment/path.py
xpl/environment/platformtype.py
xpl/exception/__init__.py
xpl/exception/singletonerror.py
xpl/filesystem/__init__.py
xpl/filesystem/directory.py
xpl/filesystem/drive.py
xpl/filesystem/entry.py
xpl/filesystem/file.py
xpl/filesystem/stroage.py
xpl/future/__init__.py
xpl/future/baseagent.py
xpl/future/basebehaviour.py
xpl/future/eventhandler.py
xpl/future/eventnode.py
xpl/future/protocol.py
xpl/generic/__init__.py
xpl/http/__init__.py
xpl/http/httpstatuserror.py
xpl/management/__init__.py
xpl/management/basemanager.py
xpl/management/baserepository.py
xpl/management/sharedclass.py
xpl/management/singleton.py
xpl/task/__init__.py
xpl/task/target.py
xpl/task/task.py
xpl/task/taskrunner.py
xpl/utility/__init__.py
xpl/utility/filefilter.py
xpl/utility/filter.py
xpl/utility/jsonutility.py
xpl/utility/logger.py
xpl/utility/loglevel.py
xid_xpl-0.0.34.dist-info/LICENSE
xid_xpl-0.0.34.dist-info/METADATA
xid_xpl-0.0.34.dist-info/WHEEL
xid_xpl-0.0.34.dist-info/top_level.txt
xid_xpl-0.0.34.dist-info/RECORD
